av2/__init__.py
av2/stream.py
av2/cli/__init__.py
av2/cli/main.py
av2/codec/__init__.py
av2/codec/context.py
av2/container/__init__.py
av2/container/core.py
av2/container/input.py
av2/container/output.py
av2/container/schemas.py
av2/container/streams.py
av2/video/__init__.py
av2/video/codeccontext.py
av2/video/stream.py
pyav2-0.0.2.dist-info/METADATA
pyav2-0.0.2.dist-info/WHEEL
pyav2-0.0.2.dist-info/entry_points.txt
pyav2-0.0.2.dist-info/top_level.txt
pyav2-0.0.2.dist-info/RECORD
